MANIFEST.in
pymdb.py
pymdbbin.cpp
setup.py
mdbtools/include/mdbtools.h
mdbtools/src/libmdb/backend.c
mdbtools/src/libmdb/catalog.c
mdbtools/src/libmdb/data.c
mdbtools/src/libmdb/dump.c
mdbtools/src/libmdb/file.c
mdbtools/src/libmdb/iconv.c
mdbtools/src/libmdb/index.c
mdbtools/src/libmdb/like.c
mdbtools/src/libmdb/map.c
mdbtools/src/libmdb/money.c
mdbtools/src/libmdb/options.c
mdbtools/src/libmdb/props.c
mdbtools/src/libmdb/sargs.c
mdbtools/src/libmdb/stats.c
mdbtools/src/libmdb/table.c
mdbtools/src/libmdb/worktable.c
mdbtools/src/libmdb/write.c
pymdb.egg-info/.DS_Store
pymdb.egg-info/PKG-INFO
pymdb.egg-info/SOURCES.txt
pymdb.egg-info/dependency_links.txt
pymdb.egg-info/requires.txt
pymdb.egg-info/top_level.txt