Metadata-Version: 1.1
Name: pymdb
Version: 0.1.73
Summary: pymdb module python biniding of mdbtools
Home-page: UNKNOWN
Author: Danny Archer
Author-email: danny@inbeta.org
License: LGPL
Keywords: microsoft,mdb,access,database,python
Platform: UNKNOWN
Classifier: Intended Audience :: Developers
Classifier: Operating System :: OS Independent
Classifier: Programming Language :: Python :: 2.7
Classifier: Programming Language :: Python :: 3.3
Classifier: Topic :: Software Development :: Libraries :: Python Modules
Classifier: Topic :: Utilities
